wired_injector/__init__.py
wired_injector/decorators.py
wired_injector/field_info.py
wired_injector/injector.py
wired_injector/operators.py
wired_injector/py.typed
wired_injector/registry.py
wired_injector/utils.py
wired_injector-0.2.0.dist-info/LICENSE.txt
wired_injector-0.2.0.dist-info/METADATA
wired_injector-0.2.0.dist-info/WHEEL
wired_injector-0.2.0.dist-info/top_level.txt
wired_injector-0.2.0.dist-info/RECORD
