Metadata-Version: 2.1
Name: wired-injector
Version: 0.2.0
Summary: Dependency injection system for wired.
Home-page: https://wired_injector.readthedocs.io
Author: Paul Everitt
Author-email: pauleveritt@me.com
License: UNKNOWN
Keywords: ioc container,inversion of control,dependency injection,service locator,singleton,service factory
Platform: UNKNOWN
Classifier: Development Status :: 4 - Beta
Classifier: Intended Audience :: Developers
Classifier: License :: OSI Approved :: MIT License
Classifier: Natural Language :: English
Classifier: Programming Language :: Python :: 3
Classifier: Programming Language :: Python :: 3.7
Classifier: Programming Language :: Python :: 3.8
Classifier: Programming Language :: Python :: 3.9
Classifier: Programming Language :: Python :: Implementation :: CPython
Classifier: Programming Language :: Python :: Implementation :: PyPy
Requires-Python: >=3.6
Requires-Dist: wired
Requires-Dist: venusian
Requires-Dist: typing-utils ; python_version < "3.8"
Requires-Dist: typing-extensions ; python_version < "3.9"
Provides-Extra: dev
Requires-Dist: mypy ; extra == 'dev'
Requires-Dist: coverage ; extra == 'dev'
Requires-Dist: pytest-coverage ; extra == 'dev'
Requires-Dist: tox ; extra == 'dev'
Requires-Dist: black ; extra == 'dev'
Requires-Dist: flake8 ; extra == 'dev'
Requires-Dist: twine ; extra == 'dev'
Requires-Dist: pre-commit ; extra == 'dev'
Requires-Dist: check-manifest ; extra == 'dev'
Provides-Extra: docs
Requires-Dist: Sphinx ; extra == 'docs'
Requires-Dist: sphinx-book-theme ; extra == 'docs'
Requires-Dist: myst-parser ; extra == 'docs'
Requires-Dist: sphinx-autodoc-typehints ; extra == 'docs'
Provides-Extra: tests
Requires-Dist: pytest ; extra == 'tests'
